{
  "levelNumber": 37,
  "size": 44,
  "steps": 56,
  "successRatio": 1,
  "type": "unroll",
  "legal": true,
  "worky": true,
  "author": "mrflip",
  "hash": "d111bd33a6f75e51e140928e67e37949",
  "path": "37-Scavenger-Chain-8.63/44.56.unroll-mrflip.asm",
  "source": "-- HUMAN RESOURCE MACHINE PROGRAM --\n-- 37-Scavenger-Chain - SIZE 44/8 - SPEED 56/63 --\n\na:\n    INBOX\nb:\n    COPYTO   22\n    COPYFROM [22]\n    OUTBOX\n    BUMPUP   22\n    COPYFROM [22]\n    JUMPN    a\n--\n    COPYTO   22\n    COPYFROM [22]\n    OUTBOX\n    BUMPUP   22\n    COPYFROM [22]\n    JUMPN    a\n--\n    COPYTO   22\n    COPYFROM [22]\n    OUTBOX\n    BUMPUP   22\n    COPYFROM [22]\n    JUMPN    a\n--\n    COPYTO   22\n    COPYFROM [22]\n    OUTBOX\n    BUMPUP   22\n    COPYFROM [22]\n    JUMPN    a\n--\n    COPYTO   22\n    COPYFROM [22]\n    OUTBOX\n    BUMPUP   22\n    COPYFROM [22]\n    JUMPN    a\n--\n    COPYTO   22\n    COPYFROM [22]\n    OUTBOX\n    BUMPUP   22\n    COPYFROM [22]\n    JUMPN    a\n--\n    COPYTO   22\n    COPYFROM [22]\n    OUTBOX\n    BUMPUP   22\n    COPYFROM [22]\n    JUMPN    a\n--\n    JUMP     b\n\n\nDEFINE LABEL 22\neJxjZ2BgSK002VZQVTh9Um1F8qTaN5FAIQbdGiZ1hlEwCkbBsAcA+Z8I0g;\n"
}